qugradlab/__init__.py
qugradlab/hilbert_spaces/__init__.py
qugradlab/hilbert_spaces/_get_digit.py
qugradlab/hilbert_spaces/_qudit_hilbert_spaces.py
qugradlab/hilbert_spaces/bosonic/__init__.py
qugradlab/hilbert_spaces/bosonic/_bosonic_hilbert_spaces.py
qugradlab/hilbert_spaces/fermionic/__init__.py
qugradlab/hilbert_spaces/fermionic/_fermionic_hilbert_spaces.py
qugradlab/hilbert_spaces/fermionic/_hamming_weight_operations.py
qugradlab/pulses/__init__.py
qugradlab/pulses/composition.py
qugradlab/pulses/filtering.py
qugradlab/pulses/sampling.py
qugradlab/pulses/invertible_functions/__init__.py
qugradlab/pulses/invertible_functions/_invertible_function.py
qugradlab/pulses/invertible_functions/packaging.py
qugradlab/pulses/invertible_functions/packaging.pyi
qugradlab/pulses/invertible_functions/scaling.py
qugradlab/pulses/invertible_functions/scaling.pyi
qugradlab/systems/__init__.py
qugradlab/systems/semiconducting/__init__.py
qugradlab/systems/semiconducting/esr/__init__.py
qugradlab/systems/semiconducting/esr/_controls.py
qugradlab/systems/semiconducting/esr/_controls.pyi
qugradlab/systems/semiconducting/esr/_device.py
qugradlab/systems/semiconducting/esr/_systems.py
qugradlab/systems/skeletons/__init__.py
qugradlab/systems/skeletons/_skeletal_system.py
qugradlab/systems/skeletons/fermionic/__init__.py
qugradlab/systems/skeletons/fermionic/_fermionic_fock_operations.py
qugradlab/systems/skeletons/fermionic/_fermionic_system.py
qugradlab/systems/skeletons/fermionic/fermionic_fock_skeleton.py
qugradlab/systems/skeletons/qubits/__init__.py
qugradlab/systems/skeletons/qubits/_qubit_system.py
qugradlab/systems/skeletons/qubits/qubit_skeleton.py
qugradlab-0.1.2.dist-info/METADATA
qugradlab-0.1.2.dist-info/WHEEL
qugradlab-0.1.2.dist-info/licenses/LICENSE
qugradlab-0.1.2.dist-info/RECORD
